igm/__init__.py
igm/conf/__init__.py
igm/conf/inquire.py
igm/conf/project.py
igm/conf/requirement.py
igm/conf/setup.py
igm/conf/template.py
igm/config/__init__.py
igm/config/meta.py
igm/entry/__init__.py
igm/entry/base.py
igm/entry/cli.py
igm/entry/dispatch.py
igm/entry/new.py
igm/entry/run.py
igm/entry/show.py
igm/env/__init__.py
igm/env/environ.py
igm/env/inquire.py
igm/env/system.py
igm/env/hardware/__init__.py
igm/env/hardware/base.py
igm/env/hardware/cpu.py
igm/env/hardware/cuda.py
igm/env/hardware/gpu.py
igm/env/hardware/memory.py
igm/env/hardware/nvidia.py
igm/env/internet/__init__.py
igm/env/internet/connect.py
igm/env/internet/net.py
igm/env/os/__init__.py
igm/env/os/system.py
igm/env/os/type.py
igm/env/python/__init__.py
igm/env/python/pip.py
igm/env/python/py.py
igm/model/__init__.py
igm/model/collection.py
igm/model/comparable.py
igm/model/memory.py
igm/model/nested.py
igm/model/percentage.py
igm/model/size.py
igm/model/version.py
igm/render/__init__.py
igm/render/archive.py
igm/render/base.py
igm/render/imports.py
igm/render/script.py
igm/render/template.py
igm/utils/__init__.py
igm/utils/archive.py
igm/utils/file.py
igm/utils/globals.py
igm/utils/path.py
igm/utils/retrieve.py
igm/utils/tqdm.py
igm/utils/url.py
igm/utils/vcs.py
sci_igm-0.0.2.dist-info/LICENSE
sci_igm-0.0.2.dist-info/METADATA
sci_igm-0.0.2.dist-info/WHEEL
sci_igm-0.0.2.dist-info/entry_points.txt
sci_igm-0.0.2.dist-info/top_level.txt
sci_igm-0.0.2.dist-info/RECORD
